opengeode_inspector/__init__.py
opengeode_inspector/__init__.pyi
opengeode_inspector/inspector.py
opengeode_inspector/inspector.pyi
opengeode_inspector/py.typed
opengeode_inspector/bin/OpenGeode-Inspector_inspector.dll
opengeode_inspector/bin/__init__.pyi
opengeode_inspector/bin/opengeode_inspector_py_inspector.cp311-win_amd64.pyd
opengeode_inspector/bin/opengeode_inspector_py_inspector.pyi
opengeode_inspector-6.8.12.dist-info/METADATA
opengeode_inspector-6.8.12.dist-info/WHEEL
opengeode_inspector-6.8.12.dist-info/top_level.txt
opengeode_inspector-6.8.12.dist-info/RECORD
