Metadata-Version: 2.4
Name: OpenGeode-Inspector
Version: 6.8.12
Summary: Open source framework for inspecting the validity of geometric models
Author-email: Geode-solutions <contact@geode-solutions.com>
License: MIT
Requires-Python: <3.13,>=3.9
Requires-Dist: opengeode-core==15.*,>=15.30.9
